webbscrapers_api/__init__.py
webbscrapers_api-0.0.2.dist-info/LICENSE
webbscrapers_api-0.0.2.dist-info/METADATA
webbscrapers_api-0.0.2.dist-info/WHEEL
webbscrapers_api-0.0.2.dist-info/top_level.txt
webbscrapers_api-0.0.2.dist-info/RECORD
