Metadata-Version: 2.1
Name: webbscrapers-api
Version: 0.0.2
Summary: Python module to access Webbscrapers API - https://webbscrapers.live
Home-page: https://github.com/edwudw/webbscrapers_api
Author: Example Author
Author-email: author@example.com
License: UNKNOWN
Platform: UNKNOWN
Classifier: Programming Language :: Python :: 3
Classifier: License :: OSI Approved :: MIT License
Classifier: Operating System :: OS Independent
Requires-Python: >=3.6
